nconf/__init__.py
nconf/lib/__init__.py
nconf/lib/decorators.py
nconf/lib/exceptions.py
nconf/lib/field.py
nconf/lib/listfield.py
nconf/lib/missing.py
nconf/lib/sectionfield.py
nconf/lib/typefield.py
nconf/lib/util.py
nconf-1.1.3.dist-info/LICENSE
nconf-1.1.3.dist-info/METADATA
nconf-1.1.3.dist-info/WHEEL
nconf-1.1.3.dist-info/top_level.txt
nconf-1.1.3.dist-info/zip-safe
nconf-1.1.3.dist-info/RECORD
