Metadata-Version: 2.1
Name: nconf
Version: 1.1.3
Summary: nconf
Home-page: UNKNOWN
Author: Natalie Fearnley
Author-email: nfearnley@gmail.com
License: MIT
Project-URL: Source, https://github.com/nfearnley/nconf
Project-URL: Tracker, https://github.com/nfearnley/nconf/issues
Keywords: conf,config,configuration,loader,ini
Platform: any
Classifier: Programming Language :: Python :: 3.9
Classifier: Operating System :: OS Independent
Classifier: License :: OSI Approved :: MIT License
Requires-Python: >=3.9
License-File: LICENSE
Provides-Extra: dev
Requires-Dist: pytest (==6.2.5) ; extra == 'dev'
Requires-Dist: flake8 (==3.9.2) ; extra == 'dev'
Requires-Dist: autopep8 (==1.5.7) ; extra == 'dev'
Requires-Dist: toml (==0.10.2) ; extra == 'dev'
